claude_cli_sdk/__init__.py
claude_cli_sdk/client.py
claude_cli_sdk/config.py
claude_cli_sdk/exceptions.py
claude_cli_sdk/hooks.py
claude_cli_sdk/models.py
claude_cli_sdk/orchestrator.py
claude_cli_sdk/parallel.py
claude_cli_sdk/py.typed
claude_cli_sdk/utils.py
claude_cli_sdk-0.2.1.dist-info/METADATA
claude_cli_sdk-0.2.1.dist-info/WHEEL
claude_cli_sdk-0.2.1.dist-info/RECORD
