Metadata-Version: 2.4
Name: claude-cli-sdk
Version: 0.2.1
Summary: Python SDK wrapping Claude CLI - Use Skills, Hooks, Slash Commands, Agents without official SDK
Project-URL: Homepage, https://github.com/chanhokim/claude-cli-sdk
Project-URL: Documentation, https://github.com/chanhokim/claude-cli-sdk#readme
Project-URL: Repository, https://github.com/chanhokim/claude-cli-sdk
Project-URL: Issues, https://github.com/chanhokim/claude-cli-sdk/issues
Author: Claude CLI SDK Contributors
License: MIT
Keywords: agent,ai,anthropic,claude,cli,llm,sdk
Classifier: Development Status :: 4 - Beta
Classifier: Intended Audience :: Developers
Classifier: License :: OSI Approved :: MIT License
Classifier: Operating System :: OS Independent
Classifier: Programming Language :: Python :: 3
Classifier: Programming Language :: Python :: 3.10
Classifier: Programming Language :: Python :: 3.11
Classifier: Programming Language :: Python :: 3.12
Classifier: Topic :: Software Development :: Libraries :: Python Modules
Classifier: Typing :: Typed
Requires-Python: >=3.10
Provides-Extra: dev
Requires-Dist: mypy>=1.0; extra == 'dev'
Requires-Dist: pytest-asyncio>=0.21; extra == 'dev'
Requires-Dist: pytest>=7.0; extra == 'dev'
Requires-Dist: ruff>=0.1; extra == 'dev'
